{"antiFeatures":{},"commandLine":["/usr/bin/fdroid update","--create-metadata"],"disabled":[],"endTimestamp":1709943224401,"failedBuilds":{},"fdroiddata":{"commitId":"260227bd20bb290fa3c987f48ff95d55a330b0b8","isDirty":true,"modifiedFiles":["config.yml","repo/index-v1.jar","repo/index-v1.json","repo/index.jar","repo/index.xml"],"untrackedFiles":["repo/icons/myicon.png"]},"noPackages":["com.airfryer.canadensis","com.airfryer.homescreen","com.airfryer.microwave.provider","com.airfryer.ms","com.airfryer.wallpaperpicker","com.goose.ch.provider","com.goose.easteregg2","com.goose.honktool","com.goose.peroxide","com.securly.pnphub","sk.styk.martin.apkanalyzer","wstxda.lineageicons"],"startTimestamp":1709961205000,"subcommand":"update"}